database_automation/__init__.py
database_automation/mongo_crud.py
Mongodb_Automation_Project-0.0.19.dist-info/METADATA
Mongodb_Automation_Project-0.0.19.dist-info/WHEEL
Mongodb_Automation_Project-0.0.19.dist-info/top_level.txt
Mongodb_Automation_Project-0.0.19.dist-info/RECORD
